prompt_galary/__init__.py
prompt_galary/main.py
prompt_galary-0.1.11.dist-info/LICENSE
prompt_galary-0.1.11.dist-info/METADATA
prompt_galary-0.1.11.dist-info/WHEEL
prompt_galary-0.1.11.dist-info/top_level.txt
prompt_galary-0.1.11.dist-info/RECORD
