Metadata-Version: 2.1
Name: prompt-galary
Version: 0.1.11
Summary: a prompt galary for llm
Home-page: https://github.com/ijaytelgote/prompt_galary
Author: Jay Telgote
Author-email: ijaytelgote@gmail.com
License: MIT
Classifier: Programming Language :: Python :: 3
Classifier: License :: OSI Approved :: MIT License
Classifier: Operating System :: OS Independent
Requires-Python: >=3.9
License-File: LICENSE
Requires-Dist: langchain-groq
Requires-Dist: pydantic
